zyxelt50/__init__.py
zyxelt50/helpers.py
zyxelt50/modem.py
zyxel_t50_modem-0.0.2.dist-info/LICENSE
zyxel_t50_modem-0.0.2.dist-info/METADATA
zyxel_t50_modem-0.0.2.dist-info/WHEEL
zyxel_t50_modem-0.0.2.dist-info/top_level.txt
zyxel_t50_modem-0.0.2.dist-info/RECORD
