Metadata-Version: 2.1
Name: zyxel-t50-modem
Version: 0.0.2
Summary: A wrapper for the Zyxel T50 modem
Home-page: https://github.com/SLG/zyxel-t50
Author: SLG
Author-email: github@slbg.nl
License: UNKNOWN
Platform: UNKNOWN
Classifier: Programming Language :: Python :: 3
Classifier: License :: OSI Approved :: MIT License
Classifier: Operating System :: OS Independent
Requires-Python: >=3.6
License-File: LICENSE
